ITHmapper/__init__.py
ITHmapper/clustering.py
ITHmapper/mapping.py
ITHmapper/meta_module.py
ITHmapper/neighbors.py
ITHmapper/pipeline.py
ITHmapper/scoring.py
ITHmapper/reference_modules/cell_state_dictionary_Bladder.json
ITHmapper/reference_modules/cell_state_dictionary_Brain.json
ITHmapper/reference_modules/cell_state_dictionary_Breast.json
ITHmapper/reference_modules/cell_state_dictionary_Colorectal.json
ITHmapper/reference_modules/cell_state_dictionary_Gastric.json
ITHmapper/reference_modules/cell_state_dictionary_Kidney_RCC.json
ITHmapper/reference_modules/cell_state_dictionary_Liver_HCC.json
ITHmapper/reference_modules/cell_state_dictionary_Lung_LUAD.json
ITHmapper/reference_modules/cell_state_dictionary_Neuroblastoma.json
ITHmapper/reference_modules/cell_state_dictionary_Ovarian_HGSOC.json
ITHmapper/reference_modules/cell_state_dictionary_Pancreas.json
ITHmapper/reference_modules/cell_state_dictionary_Prostate.json
ITHmapper/reference_modules/data_for_cell_state_dict.csv
ITHmapper/reference_modules/seed_10early_stopping_fresh_hotspot_scvi_modules_results_Bladder.csv
ITHmapper/reference_modules/seed_10early_stopping_fresh_hotspot_scvi_modules_results_Brain.csv
ITHmapper/reference_modules/seed_10early_stopping_fresh_hotspot_scvi_modules_results_Breast.csv
ITHmapper/reference_modules/seed_10early_stopping_fresh_hotspot_scvi_modules_results_Colorectal.csv
ITHmapper/reference_modules/seed_10early_stopping_fresh_hotspot_scvi_modules_results_Gastric.csv
ITHmapper/reference_modules/seed_10early_stopping_fresh_hotspot_scvi_modules_results_Kidney_RCC.csv
ITHmapper/reference_modules/seed_10early_stopping_fresh_hotspot_scvi_modules_results_Liver_CHOL.csv
ITHmapper/reference_modules/seed_10early_stopping_fresh_hotspot_scvi_modules_results_Liver_HCC.csv
ITHmapper/reference_modules/seed_10early_stopping_fresh_hotspot_scvi_modules_results_Lung_LUAD.csv
ITHmapper/reference_modules/seed_10early_stopping_fresh_hotspot_scvi_modules_results_Lung_LUSC.csv
ithmapper-0.1.6.dist-info/METADATA
ithmapper-0.1.6.dist-info/WHEEL
ithmapper-0.1.6.dist-info/licenses/LICENSE
ithmapper-0.1.6.dist-info/RECORD
