Metadata-Version: 2.4
Name: ITHmapper
Version: 0.1.6
Summary: A pipeline for mapping scRNA-seq query cells to reference cell states using Hotspot, meta-modules, and consensus profiles.
Project-URL: Homepage, https://github.com/abelson-lab/ITHmapper
Project-URL: Issues, https://github.com/abelson-lab/ITHmapper/issues
Author-email: Ido Nofech-Mozes <ido.nofechmozes@mail.utoronto.ca>
License: MIT
License-File: LICENSE
Classifier: Intended Audience :: Science/Research
Classifier: License :: OSI Approved :: MIT License
Classifier: Operating System :: OS Independent
Classifier: Programming Language :: Python :: 3
Classifier: Topic :: Scientific/Engineering :: Bio-Informatics
Requires-Python: >=3.7
Requires-Dist: anndata==0.11.4
Requires-Dist: hotspotsc==1.1.3
Requires-Dist: igraph==0.11.9
Requires-Dist: importlib-resources==6.4.0; python_version < '3.9'
Requires-Dist: louvain==0.8.2
Requires-Dist: matplotlib==3.10.3
Requires-Dist: numpy==2.2.6
Requires-Dist: pandas==2.3.1
Requires-Dist: scanpy==1.11.3
Requires-Dist: scikit-learn==1.7.0
Requires-Dist: scipy==1.15.3
Requires-Dist: seaborn==0.13.2
Requires-Dist: tqdm==4.67.1
Requires-Dist: umap-learn==0.5.9.post2
